zensols/calamr/resources/align.yml
zensols/calamr/resources/app.conf
zensols/calamr/resources/construct.yml
zensols/calamr/resources/corpus.conf
zensols/calamr/resources/default.conf
zensols/calamr/resources/defaults.conf
zensols/calamr/resources/dep.yml
zensols/calamr/resources/graphviz.yml
zensols/calamr/resources/hyperparam.yml
zensols/calamr/resources/obj.conf
zensols/calamr/resources/pkg.conf
zensols/calamr/resources/plotly.yml
zensols/calamr/resources/pyvis.yml
zensols/calamr/resources/role-nominals.json
zensols/calamr/resources/score.yml
zensols/calamr/resources/sequence.json
zensols/calamr/resources/corpus/.gitignore
zensols/calamr/resources/corpus/adhoc.conf
zensols/calamr/resources/corpus/bio.conf
zensols/calamr/resources/corpus/little-prince.conf
zensols/calamr/resources/corpus/proxy-report.conf
zensols/calamr/__init__.py
zensols/calamr/alignconst.py
zensols/calamr/aligner.py
zensols/calamr/annotate.py
zensols/calamr/app.py
zensols/calamr/attr.py
zensols/calamr/cli.py
zensols/calamr/comp.py
zensols/calamr/ctrl.py
zensols/calamr/dcomp.py
zensols/calamr/doc.py
zensols/calamr/domain.py
zensols/calamr/flow.py
zensols/calamr/flowmeta.py
zensols/calamr/morph.py
zensols/calamr/proto.py
zensols/calamr/reentrancy.py
zensols/calamr/score.py
zensols/calamr/stash.py
zensols/calamr/render/base.py
zensols/calamr/render/graphvis.py
zensols/calamr/render/plotly.py
zensols/calamr/render/pyvis.py
zensols/calamr/render/util.py
zensols/calamr/summary/alignconst.py
zensols/calamr/summary/capacity.py
zensols/calamr/summary/coref.py
zensols/calamr/summary/factory.py
zensols_calamr-0.3.0.dist-info/METADATA
zensols_calamr-0.3.0.dist-info/WHEEL
zensols_calamr-0.3.0.dist-info/entry_points.txt
zensols_calamr-0.3.0.dist-info/licenses/LICENSE.md
zensols_calamr-0.3.0.dist-info/RECORD
