Metadata-Version: 2.3
Name: zensols_calamr
Version: 0.3.0
Summary: This repository contains code for the paper and aligns the components of a bipartite source and summary AMR graph.
Project-URL: Homepage, https://github.com/plandes/calamr
Project-URL: Documentation, https://plandes.github.io/calamr
Project-URL: Repository, https://github.com/plandes/calamr.git
Project-URL: Issues, https://github.com/plandes/calamr/issues
Project-URL: Changelog, https://github.com/plandes/calamr/blob/master/CHANGELOG.md
Author-email: Paul Landes <landes@mailc.net>
License: MIT
Keywords: amr,graph,semantics
Requires-Python: <3.13,>=3.11
Requires-Dist: chart-studio~=1.1.0
Requires-Dist: igraph~=0.11.3
Requires-Dist: pyvis~=0.2.1
Requires-Dist: zensols-amr~=0.2.4
Requires-Dist: zensols-propbankdb~=0.2.1
Requires-Dist: zensols-rend
